{
  "version-v1.9.0-docs": {
    "Introduction": [
      "version-v1.9.0-intro"
    ],
    "Getting started": [
      "version-v1.9.0-getting-started-developing-with-reaction",
      "version-v1.9.0-installation",
      "version-v1.9.0-installation-osx",
      "version-v1.9.0-installation-windows",
      "version-v1.9.0-installation-linux",
      "version-v1.9.0-reaction-cli",
      "version-v1.9.0-configuration",
      "version-v1.9.0-developer-faq"
    ],
    "Plugin Tutorial": [
      "version-v1.9.0-plugin-intro-1",
      "version-v1.9.0-plugin-creating-2",
      "version-v1.9.0-plugin-layouts-3",
      "version-v1.9.0-plugin-customizing-templates-4",
      "version-v1.9.0-plugin-fixtures-5",
      "version-v1.9.0-plugin-routes-6",
      "version-v1.9.0-plugin-workflow-7",
      "version-v1.9.0-plugin-schemas-8",
      "version-v1.9.0-plugin-i18n-9",
      "version-v1.9.0-plugin-complete-10"
    ],
    "Customization Guides": [
      "version-v1.9.0-tutorial",
      "version-v1.9.0-creating-a-theme",
      "version-v1.9.0-appearance",
      "version-v1.9.0-creating-a-payment-provider",
      "version-v1.9.0-extending-product-schema-location-map",
      "version-v1.9.0-how-to-change-the-favicon",
      "version-v1.9.0-how-to-create-a-custom-homepage",
      "version-v1.9.0-testing-tutorial",
      "version-v1.9.0-testing-debugging-server-code",
      "version-v1.9.0-register-template",
      "version-v1.9.0-register-email",
      "version-v1.9.0-fixtures-images"
    ],
    "Contributing Guide": [
      "version-v1.9.0-contributing-to-reaction",
      "version-v1.9.0-styleguide",
      "version-v1.9.0-git-style-guide",
      "version-v1.9.0-react-best-practices",
      "version-v1.9.0-jsdoc-style-guide",
      "version-v1.9.0-error-handling-guide",
      "version-v1.9.0-release-process",
      "version-v1.9.0-reporting-vulnerabilities",
      "version-v1.9.0-community-channels",
      "version-v1.9.0-community-resources",
      "version-v1.9.0-community-showcase"
    ],
    "Architecture": [
      "version-v1.9.0-architecture",
      "version-v1.9.0-exports",
      "version-v1.9.0-security",
      "version-v1.9.0-simple-schema",
      "version-v1.9.0-collections",
      "version-v1.9.0-database-migrations",
      "version-v1.9.0-image-handling",
      "version-v1.9.0-routing",
      "version-v1.9.0-seo-metadata",
      "version-v1.9.0-internationalization",
      "version-v1.9.0-registry",
      "version-v1.9.0-product-variants",
      "version-v1.9.0-permissions",
      "version-v1.9.0-layout",
      "version-v1.9.0-workflow",
      "version-v1.9.0-logging",
      "version-v1.9.0-jobcontrol"
    ],
    "Core": [
      "version-v1.9.0-reaction-core",
      "version-v1.9.0-admin-views",
      "version-v1.9.0-reaction-user-accounts",
      "version-v1.9.0-reaction-alerts",
      "version-v1.9.0-analytics",
      "version-v1.9.0-email-api",
      "version-v1.9.0-i18n",
      "version-v1.9.0-reaction-shops",
      "version-v1.9.0-reaction-product-detail",
      "version-v1.9.0-reaction-products",
      "version-v1.9.0-reaction-tags",
      "version-v1.9.0-reaction-cart",
      "version-v1.9.0-reaction-shipping",
      "version-v1.9.0-reaction-payments",
      "version-v1.9.0-reaction-orders",
      "version-v1.9.0-reaction-import",
      "version-v1.9.0-reaction-inventory",
      "version-v1.9.0-reaction-localization",
      "version-v1.9.0-method-hooks",
      "version-v1.9.0-collection-hooks",
      "version-v1.9.0-event-hooks",
      "version-v1.9.0-reaction-module-cheatsheet",
      "version-v1.9.0-template-helpers",
      "version-v1.9.0-revision-api"
    ],
    "Components": [
      "version-v1.9.0-components",
      "version-v1.9.0-components-api",
      "version-v1.9.0-alerts",
      "version-v1.9.0-badge",
      "version-v1.9.0-button",
      "version-v1.9.0-cards",
      "version-v1.9.0-checkbox",
      "version-v1.9.0-clickToCopy",
      "version-v1.9.0-divider",
      "version-v1.9.0-dropDownMenu",
      "version-v1.9.0-icon",
      "version-v1.9.0-lists",
      "version-v1.9.0-media",
      "version-v1.9.0-menu",
      "version-v1.9.0-metadata",
      "version-v1.9.0-multi-select",
      "version-v1.9.0-popover",
      "version-v1.9.0-avatar",
      "version-v1.9.0-select",
      "version-v1.9.0-settings-card",
      "version-v1.9.0-slider",
      "version-v1.9.0-sortableTable",
      "version-v1.9.0-switch",
      "version-v1.9.0-tags",
      "version-v1.9.0-textfield",
      "version-v1.9.0-tooltip",
      "version-v1.9.0-translation"
    ],
    "Plugins": [
      "version-v1.9.0-packages",
      "version-v1.9.0-converting",
      "version-v1.9.0-including",
      "version-v1.9.0-payment-packages-authnet",
      "version-v1.9.0-payment-packages-braintree",
      "version-v1.9.0-payment-packages-paypal",
      "version-v1.9.0-payment-packages-stripe",
      "version-v1.9.0-taxes-packages-avalara",
      "version-v1.9.0-taxes-packages-taxcloud",
      "version-v1.9.0-packages-search"
    ],
    "Testing": [
      "version-v1.9.0-testing-reaction",
      "version-v1.9.0-acceptance-testing",
      "version-v1.9.0-react-testing",
      "version-v1.9.0-using-factories-for-testing",
      "version-v1.9.0-using-faker-for-testing",
      "version-v1.9.0-using-ci"
    ],
    "Deploying": [
      "version-v1.9.0-deploying",
      "version-v1.9.0-prerender",
      "version-v1.9.0-deploying-reaction-using-docker"
    ],
    "Store Operator's Guide": [
      "version-v1.9.0-dashboard",
      "version-v1.9.0-products",
      "version-v1.9.0-navigation-bar-and-grid",
      "version-v1.9.0-tagging",
      "version-v1.9.0-orders-admin",
      "version-v1.9.0-accounts",
      "version-v1.9.0-login-auth-services",
      "version-v1.9.0-social-settings",
      "version-v1.9.0-shop-admin",
      "version-v1.9.0-merchant-shop-setup",
      "version-v1.9.0-email-admin",
      "version-v1.9.0-localization-and-i18n",
      "version-v1.9.0-payment",
      "version-v1.9.0-catalog",
      "version-v1.9.0-tax",
      "version-v1.9.0-template",
      "version-v1.9.0-search",
      "version-v1.9.0-sms-notifications",
      "version-v1.9.0-shipping-admin",
      "version-v1.9.0-payments-discounts",
      "version-v1.9.0-faqs"
    ],
    "Guidelines": [
      "version-v1.9.0-guidelines",
      "version-v1.9.0-code-of-conduct",
      "version-v1.9.0-diversity-statement",
      "version-v1.9.0-reporting-guide",
      "version-v1.9.0-enforcement",
      "version-v1.9.0-code-of-conduct-committee",
      "version-v1.9.0-guideline-faqs",
      "version-v1.9.0-changes"
    ]
  }
}
